app/__init__.py
app/routes.py
app/run.py
app/static/css/styles.css
app/templates/empty_landing_page.html
app/templates/landing_page.html
app/templates/mtc_detail_view.html
gemtest_webapp-1.0.1.dist-info/LICENSE
gemtest_webapp-1.0.1.dist-info/METADATA
gemtest_webapp-1.0.1.dist-info/WHEEL
gemtest_webapp-1.0.1.dist-info/entry_points.txt
gemtest_webapp-1.0.1.dist-info/RECORD
