Metadata-Version: 2.3
Name: gemtest-webapp
Version: 1.0.1
Summary: Visualize metamorphic test cases from gemtest
License: MIT
Keywords: metamorphic testing,test,framework
Author: Simon Speth
Author-email: simon.speth@tum.de
Maintainer: Simon Speth
Maintainer-email: simon.speth@tum.de
Requires-Python: >=3.8,<3.14
Classifier: Development Status :: 4 - Beta
Classifier: Framework :: Pytest
Classifier: Intended Audience :: Science/Research
Classifier: License :: OSI Approved :: MIT License
Classifier: Natural Language :: English
Classifier: Operating System :: POSIX :: Linux
Classifier: Programming Language :: Python
Classifier: Programming Language :: Python :: 3
Classifier: Programming Language :: Python :: 3.8
Classifier: Programming Language :: Python :: 3.9
Classifier: Programming Language :: Python :: 3.10
Classifier: Programming Language :: Python :: 3.11
Classifier: Programming Language :: Python :: 3.12
Classifier: Programming Language :: Python :: 3.13
Classifier: Programming Language :: Python :: 3 :: Only
Classifier: Topic :: Software Development :: Libraries
Classifier: Topic :: Software Development :: Testing
Classifier: Topic :: Utilities
Requires-Dist: click (>=8.1.7,<9.0.0)
Requires-Dist: flask (>=2.1.3,<3.0.0)
Requires-Dist: pandas (>=1.4.3,<2.0.0) ; python_version >= "3.8" and python_version < "3.12"
Requires-Dist: pandas (>=2.2.3,<3.0.0) ; python_version >= "3.12" and python_version < "3.14"
Requires-Dist: pandas-stubs (>=1.4.3,<2.0.0) ; python_version >= "3.8" and python_version < "3.12"
Requires-Dist: pandas-stubs (>=2.2.3,<3.0.0) ; python_version >= "3.12" and python_version < "3.14"
Project-URL: Repository, https://github.com/tum-i4/gemtest-webapp
